{
  "string": [
    {
      "name": "module_desc",
      "value": "EggClip local clipboard sync"
    },
    {
      "name": "EntryAbility_desc",
      "value": "EggClip main application"
    },
    {
      "name": "EntryAbility_label",
      "value": "EggClip"
    },
    {
      "name": "permission_internet_reason",
      "value": "Used to connect to paired EggClip devices on the local network"
    },
    {
      "name": "permission_network_info_reason",
      "value": "Used to check network status and discover EggClip services on the local network"
    },
    {
      "name": "language_system",
      "value": "System"
    },
    {
      "name": "language_zh_cn",
      "value": "简体中文"
    },
    {
      "name": "language_en_us",
      "value": "English"
    },
    {
      "name": "language_preview",
      "value": "English interface is ready"
    },
    { "name": "ui_message_unknown", "value": "Something went wrong. Please try again." },
    { "name": "ui_pairing_initial", "value": "Paste a desktop pairing invitation to validate it." },
    { "name": "ui_pairing_input_updated", "value": "Input updated. Validate the invitation to continue." },
    { "name": "ui_pairing_paste_imported", "value": "Invitation pasted and ready for validation." },
    { "name": "ui_pairing_valid_required", "value": "Import and validate an invitation before pairing." },
    { "name": "ui_pairing_code_matched", "value": "Confirmation code matched. Sensitive invitation data was cleared." },
    { "name": "ui_pairing_completed", "value": "Pairing completed over an authenticated connection." },
    { "name": "ui_pairing_invitation_valid", "value": "Invitation is valid. Compare the confirmation code." },
    { "name": "ui_pairing_invitation_invalid", "value": "The pairing invitation is invalid or expired." },
    { "name": "ui_history_load_failed", "value": "Could not load recent history." },
    { "name": "ui_history_delete_failed", "value": "Could not delete the history item." },
    { "name": "ui_history_clear_failed", "value": "Could not clear local history." },
    { "name": "ui_history_save_failed", "value": "Could not save local history." },
    { "name": "ui_history_broadcast_allowed", "value": "The sync policy allows sending to the desktop." },
    { "name": "ui_history_broadcast_paused", "value": "Text and local history were updated, but automatic sync is off." },
    { "name": "ui_settings_read_failed", "value": "Could not load settings." },
    { "name": "ui_settings_invalid", "value": "The settings are invalid." },
    { "name": "ui_settings_save_failed", "value": "Could not save settings." },
    { "name": "ui_settings_clear_history_failed", "value": "Could not clear history." },
    { "name": "ui_trusted_name_empty", "value": "Device name cannot be empty." },
    { "name": "ui_trusted_device_missing", "value": "The trusted device is missing or revoked." },
    { "name": "ui_trusted_key_cleanup_failed", "value": "The device was revoked, but old local keys could not be fully removed." },
    { "name": "ui_clipboard_read_failed", "value": "Could not read the clipboard. Use the system PasteButton authorization." },
    { "name": "ui_clipboard_not_plain_text", "value": "The clipboard does not contain plain text." },
    { "name": "ui_clipboard_empty", "value": "The clipboard text is empty." },
    { "name": "ui_clipboard_too_large", "value": "Text is %d bytes; the limit is %d bytes." },
    { "name": "ui_clipboard_read_success", "value": "Read %d bytes of plain text." },
    { "name": "ui_clipboard_write_success", "value": "Copied %d bytes to this device." },
    { "name": "ui_clipboard_write_failed", "value": "Could not write to the local clipboard." },
    { "name": "ui_scan_empty", "value": "The QR result is empty. Scan the desktop code again." },
    { "name": "ui_scan_success", "value": "QR code scanned and ready for validation." },
    { "name": "ui_scan_failed", "value": "Scanning did not finish. Check camera permission and try again." },
    { "name": "ui_connection_waiting_title", "value": "Waiting for confirmation" },
    { "name": "ui_connection_waiting_description", "value": "Import an invitation and compare the code before connecting." },
    { "name": "ui_connection_authenticated_title", "value": "Authenticated connection" },
    { "name": "ui_connection_authenticated_description", "value": "The secure session is already online." },
    { "name": "ui_connection_preparing_title", "value": "Preparing secure handshake" },
    { "name": "ui_connection_preparing_description", "value": "Initializing local identity and CLIENT_HELLO." },
    { "name": "ui_connection_connecting_title", "value": "Connecting to desktop" },
    { "name": "ui_connection_connecting_description", "value": "Connecting to %s." },
    { "name": "ui_connection_failed_title", "value": "Secure connection failed" },
    { "name": "ui_connection_failed_description", "value": "Check the local network, pairing state, and try again." },
    { "name": "ui_connection_context_failed_title", "value": "Local identity unavailable" },
    { "name": "ui_connection_context_failed_description", "value": "The app context required for HUKS and RDB is unavailable." },
    { "name": "ui_connection_endpoint_invalid_title", "value": "Invalid desktop address" },
    { "name": "ui_connection_endpoint_invalid_description", "value": "Choose a local IPv4 address and a port from 1 to 65535." },
    { "name": "ui_connection_material_failed_title", "value": "Could not prepare secure material" },
    { "name": "ui_connection_material_failed_description", "value": "Local identity or ephemeral handshake material is unavailable." },
    { "name": "ui_connection_handshake_sent_title", "value": "Identity proof sent" },
    { "name": "ui_connection_handshake_sent_description", "value": "Waiting for the desktop identity proof." },
    { "name": "ui_connection_identity_verified_title", "value": "Desktop identity verified" },
    { "name": "ui_connection_identity_verified_description", "value": "Waiting for the desktop to complete authentication." },
    { "name": "ui_connection_saved_title", "value": "Pairing saved" },
    { "name": "ui_connection_saved_description", "value": "Trusted-device and sync-space records are stored locally." },
    { "name": "ui_connection_sync_ready_title", "value": "Secure sync ready" },
    { "name": "ui_connection_sync_ready_description", "value": "The authenticated connection can now sync plain text in both directions." },
    { "name": "ui_connection_stopped_title", "value": "Pairing stopped" },
    { "name": "ui_connection_stopped_description", "value": "Import an invitation or connect again when ready." },
    { "name": "ui_connection_revoked_title", "value": "This device was removed" },
    { "name": "ui_connection_revoked_description", "value": "Trusted reconnect stopped. Create a new invitation to pair again." },
    { "name": "ui_connection_sync_init_failed_title", "value": "Secure session online; sync initialization failed" },
    { "name": "ui_connection_sync_init_failed_description", "value": "Live sync will retry after reconnection." },
    { "name": "ui_connection_received_title", "value": "Desktop text saved securely" },
    { "name": "ui_connection_received_description", "value": "The item was encrypted into recent history and is ready to copy." },
    { "name": "ui_connection_receive_duplicate_title", "value": "Duplicate desktop item ignored" },
    { "name": "ui_connection_receive_duplicate_description", "value": "The item already exists in local history." },
    { "name": "ui_connection_receive_paused_title", "value": "Auto-receive paused" },
    { "name": "ui_connection_receive_paused_description", "value": "The desktop live item was ignored by the current sync policy." },
    { "name": "ui_connection_history_sync_title", "value": "History catch-up completed" },
    { "name": "ui_connection_history_sync_description", "value": "%d added, %d duplicates, %d retention gaps." },
    { "name": "ui_outbound_none", "value": "No local items are waiting to be sent." },
    { "name": "ui_outbound_read_failed", "value": "Could not read pending sync state; local history is preserved." },
    { "name": "ui_outbound_confirmed", "value": "All local sync items were confirmed by the desktop." },
    { "name": "ui_outbound_pending", "value": "%d local items are waiting for desktop confirmation." },
    { "name": "ui_outbound_queued", "value": "%d local items will be sent after reconnection." },
    { "name": "ui_discovery_waiting", "value": "Waiting to start local network discovery." },
    { "name": "ui_discovery_unavailable", "value": "Local network discovery is unavailable." },
    { "name": "ui_discovery_searching", "value": "Searching for desktop devices." },
    { "name": "ui_discovery_found", "value": "%d candidate addresses found. Discovery does not establish trust." },
    { "name": "ui_discovery_stopped", "value": "Local network discovery stopped." },
    { "name": "ui_poc_transport_idle", "value": "Enter a desktop IP address and port to connect manually." },
    { "name": "ui_poc_connecting", "value": "Connecting to %s." },
    { "name": "ui_poc_connected", "value": "Connected to %s. This experimental connection is not authenticated." },
    { "name": "ui_poc_closed", "value": "The desktop connection closed." },
    { "name": "ui_poc_failed", "value": "Could not connect to the desktop. Check the address, firewall, and network." },
    { "name": "ui_poc_invalid", "value": "The connection address is invalid." },
    { "name": "ui_poc_disconnected", "value": "Disconnected from the desktop." },
    { "name": "ui_poc_recent_missing", "value": "No recent successful address is available." },
    { "name": "ui_poc_background", "value": "Disconnected in the background; the app will reconnect in the foreground." },
    { "name": "ui_poc_diagnostics", "value": "Frames: %d received, %d accepted, %d rejected." }
  ]
}
